django_watermark_remastered-0.1.8.dist-info/DESCRIPTION.rst
django_watermark_remastered-0.1.8.dist-info/METADATA
django_watermark_remastered-0.1.8.dist-info/RECORD
django_watermark_remastered-0.1.8.dist-info/WHEEL
django_watermark_remastered-0.1.8.dist-info/metadata.json
django_watermark_remastered-0.1.8.dist-info/top_level.txt
watermarker/__init__.py
watermarker/admin.py
watermarker/conf.py
watermarker/models.py
watermarker/utils.py
watermarker/locale/ru/LC_MESSAGES/django.mo
watermarker/locale/ru/LC_MESSAGES/django.po
watermarker/migrations/0001_initial.py
watermarker/migrations/__init__.py
watermarker/south_migrations/0001_initial.py
watermarker/south_migrations/__init__.py
watermarker/templatetags/__init__.py
watermarker/templatetags/watermark.py
watermarker/tests/__init__.py
watermarker/tests/test_utils.py
